<?xml version="1.0" encoding="utf-8" ?>
<dwsync>
<file name="AccountIcon.png" server="u0018370.scm.tees.ac.uk//web/users/u0018370/RIA_1/" local="130262259870000000" remote="130275209400000000" Dst="1" />
<file name="ajax-loader.gif" server="u0018370.scm.tees.ac.uk//web/users/u0018370/RIA_1/" local="130262259870000000" remote="130275209400000000" Dst="1" />
<file name="jquery-mobile-logo_positive.png" server="u0018370.scm.tees.ac.uk//web/users/u0018370/RIA_1/" local="130275267185587220" remote="130275281470000000" Dst="1" />
<file name="jquery-mobile-logo_small.png" server="u0018370.scm.tees.ac.uk//web/users/u0018370/RIA_1/" local="130275220779317395" remote="130275220830000000" Dst="1" />
<file name="phonegap-logo.png" server="u0018370.scm.tees.ac.uk//web/users/u0018370/RIA_1/" local="130262259870000000" remote="130275209400000000" Dst="1" />
<file name="jquery-mobile-logo_medium.png" server="u0018370.scm.tees.ac.uk//web/users/u0018370/RIA_1/" local="130275223820000000" remote="130275224140000000" Dst="1" />
<file name="AccountIcon.png" server="u0018370.scm.tees.ac.uk//web/users/u0018370/RIA_2/" local="130262259870000000" remote="130282980740000000" Dst="1" />
<file name="ajax-loader.gif" server="u0018370.scm.tees.ac.uk//web/users/u0018370/RIA_2/" local="130262259870000000" remote="130282980740000000" Dst="1" />
<file name="jquery-mobile-logo_medium.png" server="u0018370.scm.tees.ac.uk//web/users/u0018370/RIA_2/" local="130275223820000000" remote="130282980740000000" Dst="1" />
<file name="jquery-mobile-logo_positive.png" server="u0018370.scm.tees.ac.uk//web/users/u0018370/RIA_2/" local="130275267180000000" remote="130282980740000000" Dst="1" />
<file name="jquery-mobile-logo_small.png" server="u0018370.scm.tees.ac.uk//web/users/u0018370/RIA_2/" local="130275220770000000" remote="130282980740000000" Dst="1" />
<file name="phonegap-logo.png" server="u0018370.scm.tees.ac.uk//web/users/u0018370/RIA_2/" local="130262259870000000" remote="130282980740000000" Dst="1" />
<file name="jquery-mobile-logo_positive.png" server="u0018370.scm.tees.ac.uk//web/users/u0018370/RIA_3/" local="130275267180000000" remote="130294189660000000" Dst="1" />
<file name="jquery-mobile-logo_small.png" server="u0018370.scm.tees.ac.uk//web/users/u0018370/RIA_3/" local="130275220770000000" remote="130294189660000000" Dst="1" />
<file name="jquery-mobile-logo_medium.png" server="u0018370.scm.tees.ac.uk//web/users/u0018370/RIA_3/" local="130275223820000000" remote="130294189660000000" Dst="1" />
<file name="AccountIcon.png" server="u0018370.scm.tees.ac.uk//web/users/u0018370/RIA_3/" local="130262259870000000" remote="130294193560000000" Dst="1" />
<file name="ajax-loader.gif" server="u0018370.scm.tees.ac.uk//web/users/u0018370/RIA_3/" local="130262259870000000" remote="130294193560000000" Dst="1" />
<file name="icon-72-2x.png" server="u0018370.scm.tees.ac.uk//web/users/u0018370/RIA_3/" local="130289133133011637" remote="130294193560000000" Dst="1" />
<file name="icon-72-hdpi.png" server="u0018370.scm.tees.ac.uk//web/users/u0018370/RIA_3/" local="130289133022141637" remote="130294193560000000" Dst="1" />
<file name="phonegap-logo.png" server="u0018370.scm.tees.ac.uk//web/users/u0018370/RIA_3/" local="130262259870000000" remote="130294193560000000" Dst="1" />
</dwsync>